affixapi-1.1.113.dist-info/licenses/LICENSE
openapi_client/__init__.py
openapi_client/api_client.py
openapi_client/configuration.py
openapi_client/exceptions.py
openapi_client/model_utils.py
openapi_client/rest.py
openapi_client/api/2023_03_01_api.py
openapi_client/api/__init__.py
openapi_client/api/core_api.py
openapi_client/api/management_api.py
openapi_client/api/xhr__vertically_integrated_api.py
openapi_client/apis/__init__.py
openapi_client/model/__init__.py
openapi_client/model/address_no_non_null_request.py
openapi_client/model/address_response.py
openapi_client/model/client_request.py
openapi_client/model/client_response.py
openapi_client/model/companies20230301_response.py
openapi_client/model/company_response.py
openapi_client/model/compensation_history_no_non_null_request.py
openapi_client/model/compensation_history_response.py
openapi_client/model/create_employee_request.py
openapi_client/model/create_employee_request_bank_account.py
openapi_client/model/create_employee_request_dependents.py
openapi_client/model/create_employee_request_emergency_contacts.py
openapi_client/model/create_employee_request_manager.py
openapi_client/model/currency_not_null_request.py
openapi_client/model/currency_not_null_response.py
openapi_client/model/currency_response.py
openapi_client/model/disconnect_response.py
openapi_client/model/employee_response.py
openapi_client/model/employee_response_manager.py
openapi_client/model/employees20230301_response.py
openapi_client/model/employment_history_no_non_null_request.py
openapi_client/model/employment_history_response.py
openapi_client/model/employment_status_not_null_not_nullable.py
openapi_client/model/employment_status_not_null_request.py
openapi_client/model/employment_status_response.py
openapi_client/model/group_no_null_enum_request.py
openapi_client/model/group_response.py
openapi_client/model/groups20230301_response.py
openapi_client/model/groups_no_null_enum_request.py
openapi_client/model/id_and_message_response.py
openapi_client/model/identity_response.py
affixapi-1.1.113.dist-info/METADATA
affixapi-1.1.113.dist-info/WHEEL
affixapi-1.1.113.dist-info/top_level.txt
affixapi-1.1.113.dist-info/RECORD
