Metadata-Version: 2.4
Name: affixapi
Version: 1.1.113
Summary: Affix API
Home-page: 
Author: OpenAPI Generator community
Author-email: developers@affixapi.com
Keywords: OpenAPI,OpenAPI-Generator,Affix API
Requires-Python: >=3.6
License-File: LICENSE
Requires-Dist: urllib3>=1.25.3
Requires-Dist: python-dateutil
Dynamic: author
Dynamic: author-email
Dynamic: description
Dynamic: description-content-type
Dynamic: keywords
Dynamic: license-file
Dynamic: requires-dist
Dynamic: requires-python
Dynamic: summary
